pyipp/__init__.py
pyipp/const.py
pyipp/enums.py
pyipp/exceptions.py
pyipp/ipp.py
pyipp/models.py
pyipp/parser.py
pyipp/py.typed
pyipp/serializer.py
pyipp/tags.py
pyipp-0.17.1.dist-info/LICENSE
pyipp-0.17.1.dist-info/METADATA
pyipp-0.17.1.dist-info/WHEEL
pyipp-0.17.1.dist-info/RECORD
