Metadata-Version: 2.3
Name: pyipp
Version: 0.17.1
Summary: Asynchronous Python client for Internet Printing Protocol (IPP)
License: MIT
Keywords: ipp,api,async,client,printer
Author: Chris Talkington
Author-email: chris@talkingtontech.com
Maintainer: Chris Talkington
Maintainer-email: chris@talkingtontech.com
Requires-Python: >=3.9,<4.0
Classifier: Development Status :: 4 - Beta
Classifier: Framework :: AsyncIO
Classifier: Intended Audience :: Developers
Classifier: License :: OSI Approved :: MIT License
Classifier: Natural Language :: English
Classifier: Programming Language :: Python :: 3
Classifier: Programming Language :: Python :: 3.9
Classifier: Programming Language :: Python :: 3.10
Classifier: Programming Language :: Python :: 3.11
Classifier: Programming Language :: Python :: 3.12
Classifier: Programming Language :: Python :: 3.13
Classifier: Topic :: Software Development :: Libraries :: Python Modules
Requires-Dist: aiohttp (>=3.0.0)
Requires-Dist: async-timeout (==4.0.3) ; python_version < "3.11"
Requires-Dist: awesomeversion (>=21.10.1)
Requires-Dist: backoff (>=2.2.0)
Requires-Dist: deepmerge (>=1.1.0)
Requires-Dist: yarl (>=1.6.0)
Project-URL: Bug Tracker, https://github.com/ctalkington/python-ipp/issues
Project-URL: Changelog, https://github.com/ctalkington/python-ipp/releases
Project-URL: Documentation, https://github.com/ctalkington/python-ipp
Project-URL: Homepage, https://github.com/ctalkington/python-ipp
Project-URL: Repository, https://github.com/ctalkington/python-ipp
